sfdevtoolslight/__init__.py
sfdevtoolslight/devTools/AtomicData.py
sfdevtoolslight/devTools/DatetimeTools.py
sfdevtoolslight/devTools/DiscontinueSleep.py
sfdevtoolslight/devTools/Email_Helper.py
sfdevtoolslight/devTools/FuncFifoQ.py
sfdevtoolslight/devTools/HDTimer.py
sfdevtoolslight/devTools/House_Keeper.py
sfdevtoolslight/devTools/MsgQ.py
sfdevtoolslight/devTools/SafeDict.py
sfdevtoolslight/devTools/SingletonDoubleChecked.py
sfdevtoolslight/devTools/ThreadClass.py
sfdevtoolslight/devTools/ThreadQ.py
sfdevtoolslight/devTools/__init__.py
sfdevtoolslight/observability/__init__.py
sfdevtoolslight/observability/log_helper.py
sfdevtoolslight/observability/logging_json/__init__.py
sfdevtoolslight/observability/logging_json/_formatter.py
sfdevtoolslight/observability/logging_json/version.py
sfdevtoolslight/observability/logstash/__init__.py
sfdevtoolslight/observability/logstash/formatter.py
sfdevtoolslight/observability/logstash/handler_amqp.py
sfdevtoolslight/observability/logstash/handler_tcp.py
sfdevtoolslight/observability/logstash/handler_udp.py
sfdevtoolslight/storage/__init__.py
sfdevtoolslight/storage/documentDBStorage/MongoDBCtrl.py
sfdevtoolslight/storage/documentDBStorage/__init__.py
sfdevtoolslight/storage/objectStorage/AWSObjectStorage.py
sfdevtoolslight/storage/objectStorage/__init__.py
sfdevtoolslight/storage/relationalDBStorage/PostgresDBCtrl.py
sfdevtoolslight/storage/relationalDBStorage/SqliteCtrl.py
sfdevtoolslight/storage/relationalDBStorage/__init__.py
sfdevtoolslight/storage/timeseriesDBStorage/AWSTimeSeriesStorage.py
sfdevtoolslight/storage/timeseriesDBStorage/__init__.py
sfdevtoolslight-1.2.0.dist-info/WHEEL
sfdevtoolslight-1.2.0.dist-info/METADATA
sfdevtoolslight-1.2.0.dist-info/RECORD
