Metadata-Version: 2.1
Name: sfdevtoolslight
Version: 1.2.0
Summary: 
Author: SulfredLee
Author-email: sflee1112@gmail.com
Requires-Python: >=3.8,<4.0
Classifier: Programming Language :: Python :: 3
Classifier: Programming Language :: Python :: 3.8
Classifier: Programming Language :: Python :: 3.9
Classifier: Programming Language :: Python :: 3.10
Classifier: Programming Language :: Python :: 3.11
Requires-Dist: beautifulsoup4 (>=4.12.2,<5.0.0)
Requires-Dist: openpyxl (>=3.1.2,<4.0.0)
Requires-Dist: sqlalchemy (>=2.0.23,<3.0.0)
